arxiv_tools/__init__.py
arxiv_tools/cli.py
arxiv_tools-0.2.0.dist-info/METADATA
arxiv_tools-0.2.0.dist-info/WHEEL
arxiv_tools-0.2.0.dist-info/entry_points.txt
arxiv_tools-0.2.0.dist-info/top_level.txt
arxiv_tools-0.2.0.dist-info/RECORD
