Metadata-Version: 2.1
Name: arxiv_tools
Version: 0.2.0
Summary: Default template for PDM package
Author-email: svtter <svtter@qq.com>
License: MIT
Requires-Python: <4.0,>=3.8
Requires-Dist: arxiv>=2.1.3
